langchain_google_spanner/__init__.py
langchain_google_spanner/chat_message_history.py
langchain_google_spanner/graph_qa.py
langchain_google_spanner/graph_retriever.py
langchain_google_spanner/graph_store.py
langchain_google_spanner/graph_utils.py
langchain_google_spanner/loader.py
langchain_google_spanner/prompts.py
langchain_google_spanner/py.typed
langchain_google_spanner/type_utils.py
langchain_google_spanner/vector_store.py
langchain_google_spanner/version.py
langchain_google_spanner-0.8.2.dist-info/LICENSE
langchain_google_spanner-0.8.2.dist-info/METADATA
langchain_google_spanner-0.8.2.dist-info/WHEEL
langchain_google_spanner-0.8.2.dist-info/top_level.txt
langchain_google_spanner-0.8.2.dist-info/RECORD
