Metadata-Version: 2.2
Name: langchain-google-spanner
Version: 0.8.2
Summary: LangChain integrations for Google Cloud Spanner
Author-email: Google LLC <googleapis-packages@google.com>
License: 
Project-URL: Homepage, https://github.com/googleapis/langchain-google-spanner-python
Project-URL: Repository, https://github.com/googleapis/langchain-google-spanner-python.git
Project-URL: Bug Tracker, https://github.com/googleapis/langchain-google-spanner-python/issues
Project-URL: Changelog, https://github.com/googleapis/langchain-google-spanner-python/blob/main/CHANGELOG.md
Classifier: Intended Audience :: Developers
Classifier: License :: OSI Approved :: Apache Software License
Classifier: Programming Language :: Python
Classifier: Programming Language :: Python :: 3
Classifier: Programming Language :: Python :: 3.9
Classifier: Programming Language :: Python :: 3.10
Classifier: Programming Language :: Python :: 3.11
Classifier: Programming Language :: Python :: 3.12
Requires-Python: >=3.9
License-File: LICENSE
Requires-Dist: langchain-core<1.0.0,>=0.1.25
Requires-Dist: langchain-community<1.0.0,>=0.0.18
Requires-Dist: google-cloud-spanner<4.0.0,>=3.41.0
Requires-Dist: pydantic<3.0.0,>=2.9.1
Provides-Extra: lint
Requires-Dist: black[jupyter]==24.8.0; extra == "lint"
Requires-Dist: flake8==6.1.0; extra == "lint"
Requires-Dist: isort==5.13.2; extra == "lint"
Provides-Extra: test
Requires-Dist: black[jupyter]==24.8.0; extra == "test"
Requires-Dist: bs4==0.0.2; extra == "test"
Requires-Dist: flake8==6.1.0; extra == "test"
Requires-Dist: isort==5.13.2; extra == "test"
Requires-Dist: mypy==1.11.2; extra == "test"
Requires-Dist: pytest==8.3.3; extra == "test"
Requires-Dist: pytest-asyncio==0.24.0; extra == "test"
Requires-Dist: pytest-cov==5.0.0; extra == "test"
Requires-Dist: langchain_google_vertexai==2.0.8; extra == "test"
